twitterexplorer/__init__.py
twitterexplorer/__version__.py
twitterexplorer/constants.py
twitterexplorer/converters.py
twitterexplorer/d3networks.py
twitterexplorer/defaults.py
twitterexplorer/helpers.py
twitterexplorer/languages.json
twitterexplorer/launcher.py
twitterexplorer/legacy.py
twitterexplorer/networks.py
twitterexplorer/plotting.py
twitterexplorer/streamlitutils.py
twitterexplorer/tweetcollector.py
twitterexplorer/apps/__init__.py
twitterexplorer/apps/collector.py
twitterexplorer/apps/visualizer.py
twitterexplorer/html/head.html
twitterexplorer/html/htn_body.html
twitterexplorer/html/htn_graph.js
twitterexplorer/html/rtn_body.html
twitterexplorer/html/rtn_graph.js
twitterexplorer/html/rtn_graph_private.js
twitterexplorer/html/style.css
twitterexplorer-0.7.2.dist-info/LICENSE
twitterexplorer-0.7.2.dist-info/METADATA
twitterexplorer-0.7.2.dist-info/WHEEL
twitterexplorer-0.7.2.dist-info/entry_points.txt
twitterexplorer-0.7.2.dist-info/top_level.txt
twitterexplorer-0.7.2.dist-info/zip-safe
twitterexplorer-0.7.2.dist-info/RECORD
