Metadata-Version: 2.1
Name: twitterexplorer
Version: 0.7.2
Summary: A Python tool for interactive network visualizations of Twitter data.
Home-page: http://github.com/pournaki/twitter-explorer
Author: Armin Pournaki
License: GPLv3
Keywords: networks,social media
Requires-Python: >=3.7
License-File: LICENSE
Requires-Dist: streamlit <2,>=1.7.0
Requires-Dist: tweepy <5,>=4.6.0
Requires-Dist: pandas >=1.3.4
Requires-Dist: python-igraph <1,>=0.9.8
Requires-Dist: twitwi >=0.15.0
Requires-Dist: twarc <3,>=2.9.4
Requires-Dist: ebbe >=1.13.2
